.gitignore
LICENSE
MANIFEST.in
README.md
km3net.py
km3net_logo.bmp
requirements.txt
setup.py
rainbowalga/__init__.py
rainbowalga/__main__.py
rainbowalga/__version__.py
rainbowalga/constants.py
rainbowalga/core.py
rainbowalga/gui.py
rainbowalga/hardware.py
rainbowalga/physics.py
rainbowalga/tools.py
rainbowalga.egg-info/PKG-INFO
rainbowalga.egg-info/SOURCES.txt
rainbowalga.egg-info/dependency_links.txt
rainbowalga.egg-info/entry_points.txt
rainbowalga.egg-info/requires.txt
rainbowalga.egg-info/top_level.txt
rainbowalga/data/km3net_jul13_90m_r1494.detx
rainbowalga/data/km3net_jul13_90m_r1494_corrected.detx
rainbowalga/images/km3net_logo.bmp
rainbowalga/images/km3net_logo_print.bmp
rainbowalga/tests/test_core.py
rainbowalga/tests/test_tools.py