Metadata-Version: 1.1
Name: rainbowalga
Version: 1.3
Summary: A 3D event display for KM3NeT
Home-page: http://github.com/tamasgal/rainbowalga/
Author: Tamas Gal
Author-email: tgal@km3net.de
License: UNKNOWN
Platform: any
Classifier: Development Status :: 3 - Alpha
Classifier: Intended Audience :: Developers
Classifier: Intended Audience :: Science/Research
Classifier: Programming Language :: Python
